{
    "batch-size": {
        "default": 2048,
        "type": "integer",
        "values": {
            "min": 64,
            "max": 8192
        },
        "rank": 1
    },
    "ctx-size": {
        "default": 4096,
        "type": "integer",
        "values": {
            "min": 0,
            "max": 8192
        },
        "rank": 2
    },
    "gpu-layers": {
        "default": 0,
        "type": "integer",
        "values": {
            "min": 0,
            "max": 100
        },
        "rank": 3
    },
    "ubatch-size": {
        "default": 512,
        "type": "integer",
        "values": {
            "min": 32,
            "max": 4096
        },
        "rank": 4
    },
    "no-kv-offload": {
        "default": false,
        "type": "boolean",
        "values": [
            true,
            false
        ],
        "rank": 5
    },
    "defrag-thold": {
        "default": -1.0,
        "type": "float",
        "values": {
            "min": -1.0,
            "max": 1.0
        },
        "rank": 6
    },
    "rope-scaling": {
        "default": "linear",
        "type": "enum",
        "values": [
            "none",
            "linear",
            "yarn"
        ],
        "rank": 7
    },
    "flash-attn": {
        "default": false,
        "type": "boolean",
        "values": [
            true,
            false
        ],
        "rank": 8
    },
    "numa": {
        "default": null,
        "type": "enum",
        "values": [
            "distribute",
            "isolate",
            "numactl"
        ],
        "rank": 9
    },
    "threads": {
        "default": 6,
        "type": "integer",
        "values": {
            "min": 1,
            "max": 16
        },
        "rank": 10
    },
    "top-p": {
        "default": 0.95,
        "type": "float",
        "values": {
            "min": 0.0,
            "max": 1.0
        },
        "rank": 11
    },
    "split-mode": {
        "default": "layer",
        "type": "enum",
        "values": [
            "none",
            "layer",
            "row"
        ],
        "rank": 12
    },
    "top-k": {
        "default": 40,
        "type": "integer",
        "values": {
            "min": 1,
            "max": 100
        },
        "rank": 13
    },
    "cpu-strict": {
        "default": 0,
        "type": "enum",
        "values": [
            0,
            1
        ],
        "rank": 14
    },
    "draft": {
        "default": 5,
        "type": "integer",
        "values": {
            "min": 1,
            "max": 16
        },
        "rank": 15
    },
    "threads-batch": {
        "default": 6,
        "type": "integer",
        "values": {
            "min": 1,
            "max": 16
        },
        "rank": 16
    },
    "cont-batching": {
        "default": true,
        "type": "boolean",
        "values": [
            true,
            false
        ],
        "rank": 17
    },
    "parallel": {
        "default": 1,
        "type": "integer",
        "values": {
            "min": 1,
            "max": 8
        },
        "rank": 18
    },
    "no-mmap": {
        "default": false,
        "type": "boolean",
        "values": [
            true,
            false
        ],
        "rank": 19
    },
    "mlock": {
        "default": false,
        "type": "boolean",
        "values": [
            true,
            false
        ],
        "rank": 20
    },
    "no-cont-batching": {
        "default": false,
        "type": "boolean",
        "values": [
            true,
            false
        ],
        "rank": 21
    }
}
